crafter/__init__.py
crafter/core.py
crafter/craft_utils.py
crafter/file_utils.py
crafter/image_utils.py
crafter/predict.py
crafter/resources/__init__.py
crafter/resources/craftnet.onnx
crafter/resources/refinenet.onnx
pycrafter-0.0.7.dist-info/METADATA
pycrafter-0.0.7.dist-info/WHEEL
pycrafter-0.0.7.dist-info/licenses/LICENSE
pycrafter-0.0.7.dist-info/RECORD
